README.rst
setup.py
aws_tools/__init__.py
aws_tools/dynamodb_handler.py
aws_tools/s3_handler.py
client/__init__.py
client/client_callback.py
client/client_webhook.py
converters/__init__.py
converters/convert_logger.py
converters/converter.py
converters/md2html_converter.py
converters/usfm2html_converter.py
converters/templates/bible-template.html
converters/templates/obs-template.html
door43_tools/__init__.py
door43_tools/bible_books.py
door43_tools/language_handler.py
door43_tools/logger.py
door43_tools/manifest_handler.py
door43_tools/obs_data.py
door43_tools/obs_handler.py
door43_tools/preprocessors.py
door43_tools/project_deployer.py
door43_tools/templaters.py
general_tools/__init__.py
general_tools/file_utils.py
general_tools/print_utils.py
general_tools/smartquotes.py
general_tools/url_utils.py
gogs_tools/__init__.py
gogs_tools/gogs_handler.py
lambda_handlers/__init__.py
lambda_handlers/client_callback_handler.py
lambda_handlers/client_webhook_handler.py
lambda_handlers/convert_handler.py
lambda_handlers/dashboad_handler.py
lambda_handlers/door43_deploy_handler.py
lambda_handlers/handler.py
lambda_handlers/list_endpoints_handler.py
lambda_handlers/list_jobs_handler.py
lambda_handlers/register_module_handler.py
lambda_handlers/request_job_handler.py
lambda_handlers/start_job_handler.py
manager/__init__.py
manager/job.py
manager/manager.py
manager/module.py
manager/object.py
tx_manager_test1.egg-info/PKG-INFO
tx_manager_test1.egg-info/SOURCES.txt
tx_manager_test1.egg-info/dependency_links.txt
tx_manager_test1.egg-info/requires.txt
tx_manager_test1.egg-info/top_level.txt