Metadata-Version: 1.1
Name: tx-manager-test1
Version: 0.2.3
Summary: Classes for executing tX Manager
Home-page: https://github.org/unfoldingWord-dev/tx-manager
Author: unfoldingWord
Author-email: info@unfoldingword.org
License: MIT
Keywords: tX manager,unfoldingword,usfm,md2html,usfm2html
Platform: UNKNOWN
Classifier: License :: OSI Approved :: MIT License
Classifier: Programming Language :: Python :: 2.7
